{
  "required": true,
  "package": "net.zaharenko424.a_changed.mixin",
  "compatibilityLevel": "JAVA_17",
  "minVersion": "0.8.5",
  "injectors": {
    "defaultRequire": 1
  },
  "mixins": [
    "entity.MixinCreeper",
    "entity.MixinEntity",
    "entity.MixinIronGolem",
    "entity.MixinLivingEntity",
    "entity.MixinPlayer",
    "MixinServerGamePacketListenerImpl",
    "MixinSimpleBlockFeature",
    "entity.MixinWanderingTrader",
    "entityai.MixinHurtByTargetGoal",
    "entityai.MixinPhantomSweepAttackGoal",
    "entityai.MixinVillagerHostileSensor"
  ],
  "client": [
    "client.MixinBlockModelShaper",
    "client.MixinGui",
    "client.MixinLevelRenderer",
    "client.MixinLightTexture",
    "client.renderer.MixinFallingBlockRenderer",
    "client.renderer.MixinFogRenderer",
    "client.renderer.MixinGameRenderer",
    "client.renderer.MixinItemRenderer",
    "client.renderer.MixinLivingEntityRenderer",
    "client.renderer.MixinPlayerRenderer"
  ]
}